Metadata-Version: 2.1
Name: SciANN-macos
Version: 0.6.7.1
Summary: A Keras/Tensorflow wrapper for scientific computations and physics-informed deep learning using artificial neural networks.
Home-page: https://github.com/sciann/sciann
Author: Ehsan Haghighat
Author-email: ehsan@sciann.com
License: MIT
Classifier: Development Status :: 4 - Beta
Classifier: Intended Audience :: Developers
Classifier: Intended Audience :: Education
Classifier: Intended Audience :: Science/Research
Classifier: License :: OSI Approved :: MIT License
Classifier: Programming Language :: Python :: 3
Classifier: Programming Language :: Python :: 3.8
Classifier: Topic :: Software Development :: Libraries
Classifier: Topic :: Software Development :: Libraries :: Python Modules
Provides-Extra: visualize
Provides-Extra: tests
License-File: LICENSE
